[
    {
        "userName": "@nanilsin",
        "fullname": "shelton vintano",
        "password": "6512bd43d9caa6e02c990b0a82652dca",
        "email": "narcisopascoal97@gmail.com",
        "turma": "A",
        "isAproved": 1
    },
    {
        "userName": "cheche",
        "fullname": "cheche che",
        "password": "81dc9bdb52d04dc20036dbd8313ed055",
        "email": "magicc@gmail.com",
        "turma": "A",
        "isAproved": 1
    },
    {
        "userName": "l@stuser",
        "fullname": "last last",
        "password": "81dc9bdb52d04dc20036dbd8313ed055",
        "email": "last@gmail.com",
        "turma": "A",
        "isAproved": 1
    },
    {
        "userName": "bubufilho",
        "fullname": "Booststrape filho",
        "password": "d0fb963ff976f9c37fc81fe03c21ea7b",
        "email": "bubufilho@gmail.com",
        "turma": "A",
        "isAproved": 1
    },
    {
        "userName": "bubufilho",
        "fullname": "NANY shelton vintano william",
        "password": "d0fb963ff976f9c37fc81fe03c21ea7b",
        "email": "narcisopascoal97@gmail.com",
        "turma": "B"
    },
    {
        "userName": "pax",
        "fullname": "pax pax",
        "password": "202cb962ac59075b964b07152d234b70",
        "email": "scoal97@gmail.com",
        "turma": "A",
        "isAproved": 1
    },
    {
        "userName": "pax",
        "fullname": "pax pax",
        "password": "202cb962ac59075b964b07152d234b70",
        "email": "scoal97@gmail.com",
        "turma": "B",
        "isAproved": 1
    },
    {
        "userName": "pax",
        "fullname": "Paxcoal Pax",
        "password": "d0fb963ff976f9c37fc81fe03c21ea7b",
        "email": "scoal97@gmail.com",
        "turma": "H",
        "isAproved": 1
    }
]